odoo/addons/product_brand_stock_account/README.rst
odoo/addons/product_brand_stock_account/__init__.py
odoo/addons/product_brand_stock_account/__manifest__.py
odoo/addons/product_brand_stock_account/i18n/es.po
odoo/addons/product_brand_stock_account/i18n/it.po
odoo/addons/product_brand_stock_account/i18n/product_brand_stock_account.pot
odoo/addons/product_brand_stock_account/models/__init__.py
odoo/addons/product_brand_stock_account/models/stock_valuation_layer.py
odoo/addons/product_brand_stock_account/readme/CONTRIBUTORS.rst
odoo/addons/product_brand_stock_account/readme/DESCRIPTION.rst
odoo/addons/product_brand_stock_account/readme/USAGE.rst
odoo/addons/product_brand_stock_account/static/description/icon.png
odoo/addons/product_brand_stock_account/static/description/index.html
odoo/addons/product_brand_stock_account/views/stock_valuation_layer_views.xml
odoo_addon_product_brand_stock_account-16.0.1.0.0.5.dist-info/METADATA
odoo_addon_product_brand_stock_account-16.0.1.0.0.5.dist-info/WHEEL
odoo_addon_product_brand_stock_account-16.0.1.0.0.5.dist-info/top_level.txt
odoo_addon_product_brand_stock_account-16.0.1.0.0.5.dist-info/RECORD
