Metadata-Version: 2.1
Name: odoo-addon-product-brand-stock-account
Version: 16.0.1.0.0.5
Summary: This module allows to work with product_brand in Stock Account.
Home-page: https://github.com/OCA/brand
Author: Odoo Community Association (OCA)
Author-email: support@odoo-community.org
License: AGPL-3
Platform: UNKNOWN
Classifier: Programming Language :: Python
Classifier: Framework :: Odoo
Classifier: Framework :: Odoo :: 16.0
Classifier: License :: OSI Approved :: GNU Affero General Public License v3
Requires-Python: >=3.10
Requires-Dist: odoo-addon-product-brand <16.1dev,>=16.0dev
Requires-Dist: odoo <16.1dev,>=16.0a
